colour_runner/__init__.py
colour_runner/django_runner.py
colour_runner/result.py
colour_runner/runner.py
colour_runner-0.1.0.dist-info/METADATA
colour_runner-0.1.0.dist-info/RECORD
colour_runner-0.1.0.dist-info/WHEEL
colour_runner-0.1.0.dist-info/top_level.txt
