Metadata-Version: 2.1
Name: colour-runner
Version: 0.1.0
Summary: Colour formatting for unittest tests
Home-page: https://github.com/meshy/colour-runner
Author: Charlie Denton
Author-email: charlie@meshy.co.uk
License: MIT
Keywords: unittest colour color output
Platform: UNKNOWN
Classifier: Development Status :: 3 - Alpha
Classifier: Intended Audience :: Developers
Classifier: License :: OSI Approved :: MIT License
Classifier: Programming Language :: Python :: 2
Classifier: Programming Language :: Python :: 2.7
Classifier: Programming Language :: Python :: 3
Classifier: Programming Language :: Python :: 3.3
Classifier: Programming Language :: Python :: 3.4
Classifier: Programming Language :: Python :: 3.5
Classifier: Topic :: Software Development :: Testing
Requires-Dist: blessings
Requires-Dist: pygments
